arc_tools/__init__.py
arc_tools/__main__.py
arc_tools/main.py
arc_tools/makearchive.py
arc_tools/unarchivate.py
arc_tools/utils.py
arc_tools-0.2.4.dist-info/METADATA
arc_tools-0.2.4.dist-info/WHEEL
arc_tools-0.2.4.dist-info/top_level.txt
arc_tools-0.2.4.dist-info/RECORD
