Metadata-Version: 2.1
Name: arc-tools
Version: 0.2.4
Summary: Simple cli arc helper
Home-page: https://github.com/Reglament989/Compressor
Author: Reglament989
Author-email: officialreglament989@protonmail.ch
License: UNKNOWN
Platform: UNKNOWN
Requires-Python: >=3.8
